{"data":[[null,null,null,null,null,null,null,null,null,null,null,null,null,null,null,null,null,null,null,null],[null,null,null,null,null,null,null,null,null,null,null,null,null,null,null,null,null,null,null,null],[null,null,null,null,null,null,null,null,null,{"type":0,"config":{},"position":{"x":2,"y":9},"texCoords":[{"x":130,"y":0},{"x":130,"y":0},{"x":130,"y":0},{"x":130,"y":0}],"collidable":true},{"type":0,"config":{},"position":{"x":2,"y":10},"texCoords":[{"x":130,"y":0},{"x":130,"y":0},{"x":130,"y":0},{"x":130,"y":0}],"collidable":true},{"type":0,"config":{},"position":{"x":2,"y":11},"texCoords":[{"x":130,"y":0},{"x":130,"y":0},{"x":130,"y":0},{"x":130,"y":0}],"collidable":true},{"type":0,"config":{},"position":{"x":2,"y":12},"texCoords":[{"x":130,"y":0},{"x":130,"y":0},{"x":130,"y":0},{"x":130,"y":0}],"collidable":true},{"type":0,"config":{},"position":{"x":2,"y":13},"texCoords":[{"x":130,"y":0},{"x":130,"y":0},{"x":130,"y":0},{"x":130,"y":0}],"collidable":true},null,null,null,null,null,null],[null,null,null,null,null,null,null,null,null,{"type":0,"config":{},"position":{"x":3,"y":9},"texCoords":[{"x":130,"y":0},{"x":130,"y":0},{"x":130,"y":0},{"x":130,"y":0}],"collidable":true},null,null,null,{"type":0,"config":{},"position":{"x":3,"y":13},"texCoords":[{"x":130,"y":0},{"x":130,"y":0},{"x":130,"y":0},{"x":130,"y":0}],"collidable":true},null,null,null,null,null,null],[null,null,null,null,null,null,null,null,null,{"type":0,"config":{},"position":{"x":4,"y":9},"texCoords":[{"x":130,"y":0},{"x":130,"y":0},{"x":130,"y":0},{"x":130,"y":0}],"collidable":true},null,null,null,{"type":0,"config":{},"position":{"x":4,"y":13},"texCoords":[{"x":130,"y":0},{"x":130,"y":0},{"x":130,"y":0},{"x":130,"y":0}],"collidable":true},null,null,null,null,null,null],[null,null,null,null,null,null,null,{"type":0,"config":{},"position":{"x":5,"y":7},"texCoords":[{"x":0,"y":0},{"x":0,"y":0},{"x":0,"y":0},{"x":0,"y":0}],"collidable":true},{"type":0,"config":{},"position":{"x":5,"y":8},"texCoords":[{"x":0,"y":0},{"x":0,"y":0},{"x":0,"y":0},{"x":0,"y":0}],"collidable":true},{"type":0,"config":{},"position":{"x":5,"y":9},"texCoords":[{"x":0,"y":0},{"x":0,"y":0},{"x":0,"y":0},{"x":0,"y":0}],"collidable":true},{"type":0,"config":{},"position":{"x":5,"y":10},"texCoords":[{"x":0,"y":0},{"x":0,"y":0},{"x":260,"y":0},{"x":0,"y":0}],"collidable":true},{"type":2,"config":{"openness":0,"perpOffset":0.5},"position":{"x":5,"y":11},"texCoords":[{"x":195,"y":0},{"x":195,"y":0},{"x":195,"y":0},{"x":195,"y":0}],"collidable":true},{"type":0,"config":{},"position":{"x":5,"y":12},"texCoords":[{"x":260,"y":0},{"x":0,"y":0},{"x":0,"y":0},{"x":0,"y":0}],"collidable":true},{"type":0,"config":{},"position":{"x":5,"y":13},"texCoords":[{"x":0,"y":0},{"x":0,"y":0},{"x":0,"y":0},{"x":0,"y":0}],"collidable":true},{"type":0,"config":{},"position":{"x":5,"y":14},"texCoords":[{"x":0,"y":0},{"x":0,"y":0},{"x":0,"y":0},{"x":0,"y":0}],"collidable":true},{"type":0,"config":{},"position":{"x":5,"y":15},"texCoords":[{"x":0,"y":0},{"x":0,"y":0},{"x":0,"y":0},{"x":0,"y":0}],"collidable":true},null,null,null,null],[null,null,null,null,null,null,null,{"type":0,"config":{},"position":{"x":6,"y":7},"texCoords":[{"x":0,"y":0},{"x":0,"y":0},{"x":0,"y":0},{"x":0,"y":0}],"collidable":true},null,null,null,null,null,null,null,{"type":0,"config":{},"position":{"x":6,"y":15},"texCoords":[{"x":0,"y":0},{"x":0,"y":0},{"x":0,"y":0},{"x":0,"y":0}],"collidable":true},null,null,null,null],[null,null,null,null,null,null,null,{"type":0,"config":{},"position":{"x":7,"y":7},"texCoords":[{"x":0,"y":0},{"x":0,"y":0},{"x":0,"y":0},{"x":0,"y":0}],"collidable":true},null,null,null,null,null,null,null,{"type":0,"config":{},"position":{"x":7,"y":15},"texCoords":[{"x":0,"y":0},{"x":0,"y":0},{"x":0,"y":0},{"x":0,"y":0}],"collidable":true},{"type":0,"config":{},"position":{"x":7,"y":16},"texCoords":[{"x":130,"y":0},{"x":130,"y":0},{"x":130,"y":0},{"x":130,"y":0}],"collidable":true},{"type":0,"config":{},"position":{"x":7,"y":17},"texCoords":[{"x":130,"y":0},{"x":130,"y":0},{"x":130,"y":0},{"x":130,"y":0}],"collidable":true},{"type":0,"config":{},"position":{"x":7,"y":18},"texCoords":[{"x":130,"y":0},{"x":130,"y":0},{"x":130,"y":0},{"x":130,"y":0}],"collidable":true},null],[null,null,null,null,{"type":0,"config":{},"position":{"x":8,"y":4},"texCoords":[{"x":65,"y":0},{"x":65,"y":0},{"x":65,"y":0},{"x":65,"y":0}],"collidable":true},{"type":0,"config":{},"position":{"x":8,"y":5},"texCoords":[{"x":65,"y":0},{"x":65,"y":0},{"x":65,"y":0},{"x":65,"y":0}],"collidable":true},{"type":0,"config":{},"position":{"x":8,"y":6},"texCoords":[{"x":65,"y":0},{"x":65,"y":0},{"x":65,"y":0},{"x":65,"y":0}],"collidable":true},{"type":0,"config":{},"position":{"x":8,"y":7},"texCoords":[{"x":0,"y":0},{"x":0,"y":0},{"x":0,"y":0},{"x":0,"y":0}],"collidable":true},null,null,null,null,null,null,null,{"type":0,"config":{},"position":{"x":8,"y":15},"texCoords":[{"x":0,"y":0},{"x":260,"y":0},{"x":0,"y":0},{"x":0,"y":0}],"collidable":true},null,null,{"type":0,"config":{},"position":{"x":8,"y":18},"texCoords":[{"x":130,"y":0},{"x":130,"y":0},{"x":130,"y":0},{"x":130,"y":0}],"collidable":true},null],[null,null,null,null,{"type":0,"config":{},"position":{"x":9,"y":4},"texCoords":[{"x":65,"y":0},{"x":65,"y":0},{"x":65,"y":0},{"x":65,"y":0}],"collidable":true},null,null,{"type":0,"config":{},"position":{"x":9,"y":7},"texCoords":[{"x":0,"y":0},{"x":260,"y":0},{"x":0,"y":0},{"x":0,"y":0}],"collidable":true},null,null,null,null,{"type":5,"config":{},"position":{"x":9,"y":12},"texCoords":[{"x":0,"y":65}],"collidable":false},null,null,{"type":2,"config":{"openness":0,"perpOffset":0.5},"position":{"x":9,"y":15},"texCoords":[{"x":195,"y":0},{"x":195,"y":0},{"x":195,"y":0},{"x":195,"y":0}],"collidable":true},null,null,{"type":0,"config":{},"position":{"x":9,"y":18},"texCoords":[{"x":130,"y":0},{"x":130,"y":0},{"x":130,"y":0},{"x":130,"y":0}],"collidable":true},null],[null,null,null,null,{"type":0,"config":{},"position":{"x":10,"y":4},"texCoords":[{"x":65,"y":0},{"x":65,"y":0},{"x":65,"y":0},{"x":65,"y":0}],"collidable":true},null,null,{"type":2,"config":{"openness":0,"perpOffset":0.5},"position":{"x":10,"y":7},"texCoords":[{"x":195,"y":0},{"x":195,"y":0},{"x":195,"y":0},{"x":195,"y":0}],"collidable":true},null,null,null,null,null,null,null,{"type":0,"config":{},"position":{"x":10,"y":15},"texCoords":[{"x":0,"y":0},{"x":0,"y":0},{"x":0,"y":0},{"x":260,"y":0}],"collidable":true},null,null,{"type":0,"config":{},"position":{"x":10,"y":18},"texCoords":[{"x":130,"y":0},{"x":130,"y":0},{"x":130,"y":0},{"x":130,"y":0}],"collidable":true},null],[null,null,null,null,{"type":0,"config":{},"position":{"x":11,"y":4},"texCoords":[{"x":65,"y":0},{"x":65,"y":0},{"x":65,"y":0},{"x":65,"y":0}],"collidable":true},null,null,{"type":0,"config":{},"position":{"x":11,"y":7},"texCoords":[{"x":0,"y":0},{"x":0,"y":0},{"x":0,"y":0},{"x":260,"y":0}],"collidable":true},null,null,null,null,null,null,null,{"type":0,"config":{},"position":{"x":11,"y":15},"texCoords":[{"x":0,"y":0},{"x":0,"y":0},{"x":0,"y":0},{"x":0,"y":0}],"collidable":true},{"type":0,"config":{},"position":{"x":11,"y":16},"texCoords":[{"x":130,"y":0},{"x":130,"y":0},{"x":130,"y":0},{"x":130,"y":0}],"collidable":true},{"type":0,"config":{},"position":{"x":11,"y":17},"texCoords":[{"x":130,"y":0},{"x":130,"y":0},{"x":130,"y":0},{"x":130,"y":0}],"collidable":true},{"type":0,"config":{},"position":{"x":11,"y":18},"texCoords":[{"x":130,"y":0},{"x":130,"y":0},{"x":130,"y":0},{"x":130,"y":0}],"collidable":true},null],[null,null,null,null,{"type":0,"config":{},"position":{"x":12,"y":4},"texCoords":[{"x":65,"y":0},{"x":65,"y":0},{"x":65,"y":0},{"x":65,"y":0}],"collidable":true},{"type":0,"config":{},"position":{"x":12,"y":5},"texCoords":[{"x":65,"y":0},{"x":65,"y":0},{"x":65,"y":0},{"x":65,"y":0}],"collidable":true},{"type":0,"config":{},"position":{"x":12,"y":6},"texCoords":[{"x":65,"y":0},{"x":65,"y":0},{"x":65,"y":0},{"x":65,"y":0}],"collidable":true},{"type":0,"config":{},"position":{"x":12,"y":7},"texCoords":[{"x":0,"y":0},{"x":0,"y":0},{"x":0,"y":0},{"x":0,"y":0}],"collidable":true},null,null,null,null,null,null,null,{"type":0,"config":{},"position":{"x":12,"y":15},"texCoords":[{"x":0,"y":0},{"x":0,"y":0},{"x":0,"y":0},{"x":0,"y":0}],"collidable":true},null,null,null,null],[null,null,null,null,null,null,null,{"type":0,"config":{},"position":{"x":13,"y":7},"texCoords":[{"x":0,"y":0},{"x":0,"y":0},{"x":0,"y":0},{"x":0,"y":0}],"collidable":true},null,null,null,null,null,null,null,{"type":0,"config":{},"position":{"x":13,"y":15},"texCoords":[{"x":0,"y":0},{"x":0,"y":0},{"x":0,"y":0},{"x":0,"y":0}],"collidable":true},null,null,null,null],[null,null,null,null,null,null,null,{"type":0,"config":{},"position":{"x":14,"y":7},"texCoords":[{"x":0,"y":0},{"x":0,"y":0},{"x":0,"y":0},{"x":0,"y":0}],"collidable":true},{"type":0,"config":{},"position":{"x":14,"y":8},"texCoords":[{"x":0,"y":0},{"x":0,"y":0},{"x":0,"y":0},{"x":0,"y":0}],"collidable":true},{"type":0,"config":{},"position":{"x":14,"y":9},"texCoords":[{"x":0,"y":0},{"x":0,"y":0},{"x":0,"y":0},{"x":0,"y":0}],"collidable":true},{"type":0,"config":{},"position":{"x":14,"y":10},"texCoords":[{"x":0,"y":0},{"x":0,"y":0},{"x":260,"y":0},{"x":0,"y":0}],"collidable":true},{"type":2,"config":{"openness":0,"perpOffset":0.5},"position":{"x":14,"y":11},"texCoords":[{"x":195,"y":0},{"x":195,"y":0},{"x":195,"y":0},{"x":195,"y":0}],"collidable":true},{"type":0,"config":{},"position":{"x":14,"y":12},"texCoords":[{"x":260,"y":0},{"x":0,"y":0},{"x":0,"y":0},{"x":0,"y":0}],"collidable":true},{"type":0,"config":{},"position":{"x":14,"y":13},"texCoords":[{"x":0,"y":0},{"x":0,"y":0},{"x":0,"y":0},{"x":0,"y":0}],"collidable":true},{"type":0,"config":{},"position":{"x":14,"y":14},"texCoords":[{"x":0,"y":0},{"x":0,"y":0},{"x":0,"y":0},{"x":0,"y":0}],"collidable":true},{"type":0,"config":{},"position":{"x":14,"y":15},"texCoords":[{"x":0,"y":0},{"x":0,"y":0},{"x":0,"y":0},{"x":0,"y":0}],"collidable":true},null,null,null,null],[null,null,null,null,null,null,null,null,null,{"type":0,"config":{},"position":{"x":15,"y":9},"texCoords":[{"x":65,"y":0},{"x":65,"y":0},{"x":65,"y":0},{"x":65,"y":0}],"collidable":true},null,null,null,{"type":0,"config":{},"position":{"x":15,"y":13},"texCoords":[{"x":65,"y":0},{"x":65,"y":0},{"x":65,"y":0},{"x":65,"y":0}],"collidable":true},null,null,null,null,null,null],[null,null,null,null,null,null,null,null,null,{"type":0,"config":{},"position":{"x":16,"y":9},"texCoords":[{"x":65,"y":0},{"x":65,"y":0},{"x":65,"y":0},{"x":65,"y":0}],"collidable":true},null,null,null,{"type":0,"config":{},"position":{"x":16,"y":13},"texCoords":[{"x":65,"y":0},{"x":65,"y":0},{"x":65,"y":0},{"x":65,"y":0}],"collidable":true},null,null,null,null,null,null],[null,null,null,null,null,null,null,null,null,{"type":0,"config":{},"position":{"x":17,"y":9},"texCoords":[{"x":65,"y":0},{"x":65,"y":0},{"x":65,"y":0},{"x":65,"y":0}],"collidable":true},{"type":0,"config":{},"position":{"x":17,"y":10},"texCoords":[{"x":65,"y":0},{"x":65,"y":0},{"x":65,"y":0},{"x":65,"y":0}],"collidable":true},{"type":0,"config":{},"position":{"x":17,"y":11},"texCoords":[{"x":65,"y":0},{"x":65,"y":0},{"x":65,"y":0},{"x":65,"y":0}],"collidable":true},{"type":0,"config":{},"position":{"x":17,"y":12},"texCoords":[{"x":65,"y":0},{"x":65,"y":0},{"x":65,"y":0},{"x":65,"y":0}],"collidable":true},{"type":0,"config":{},"position":{"x":17,"y":13},"texCoords":[{"x":65,"y":0},{"x":65,"y":0},{"x":65,"y":0},{"x":65,"y":0}],"collidable":true},null,null,null,null,null,null],[null,null,null,null,null,null,null,null,null,null,null,null,null,null,null,null,null,null,null,null],[null,null,null,null,null,null,null,null,null,null,null,null,null,null,null,null,null,null,null,null]],"width":20,"height":20}
